{
  "title": "Innovative Collaborative Curious",
  "text": "I am driven by a desire to continuously improve the work that I put forth.",
  "section": [
    {
      "title": "Why innovative?",
      "content": "I enjoy making things more efficient and effective, so innovation is a core part of me.",
      "icon": "notes.svg"
    },
    {
      "title": "Why curious?",
      "content": "How can one continue to improve without the continuous desire to search out new knowledge?",
      "icon": "notes.svg"
    }
  ]
}